ecowatti/__init__.py
ecowatti/__main__.py
ecowatti-1.0.0.dist-info/METADATA
ecowatti-1.0.0.dist-info/WHEEL
ecowatti-1.0.0.dist-info/licenses/LICENSE
ecowatti-1.0.0.dist-info/RECORD
