Metadata-Version: 2.1
Name: ecowatti
Version: 1.0.0
Summary: Read values from Jäspi Ecowatti boiler
Project-URL: Homepage, https://github.com/lemanjo/ecowatti
Author-email: Jussi Rosenberg <jussi.rosenberg@iki.fi>
License-File: LICENSE
Keywords: ecowatti,jäspi
Classifier: License :: OSI Approved :: MIT License
Classifier: Operating System :: OS Independent
Classifier: Programming Language :: Python :: 3
Requires-Python: >=3.8
Requires-Dist: crc>=4.1.0
Requires-Dist: pyserial>=3.5
